[
    {
        "_id": 1,
        "skillName": "React JS",
        "proficiencyLevel": 4,
        "image": "https://cdn.jsdelivr.net/gh/devicons/devicon/icons/react/react-original-wordmark.svg",
        "category": "Frontend",
        "description":"I know this language"
    },
    {
        "_id": 2,
        "skillName": "Node JS",
        "proficiencyLevel": 2,
        "image": "https://cdn.jsdelivr.net/gh/devicons/devicon/icons/nodejs/nodejs-plain-wordmark.svg",
        "category": "Backend",
        "description":""
    },
    {
        "_id": 3,
        "skillName": "MongoDB",
        "proficiencyLevel": 4,
        "image": "https://cdn.jsdelivr.net/gh/devicons/devicon/icons/mongodb/mongodb-original-wordmark.svg",
        "category": "Backend"
    },
    {
        "_id": 4,
        "skillName": "Android Studio",
        "proficiencyLevel": 3,
        "image": "https://cdn.jsdelivr.net/gh/devicons/devicon/icons/android/android-plain.svg",
        "category": "Frontend"
    },
    {
        "_id": 5,
        "skillName": "C#",
        "proficiencyLevel": 3,
        "image": "https://cdn.jsdelivr.net/gh/devicons/devicon/icons/csharp/csharp-original.svg",
        "category": "Frontend"
    },
    {
        "_id": 6,
        "skillName": "PHP",
        "proficiencyLevel": 2,
        "image": "https://cdn.jsdelivr.net/gh/devicons/devicon/icons/php/php-plain.svg",
        "category": "Frontend"
    },
    {
        "_id": 7,
        "skillName": "Github",
        "proficiencyLevel": 5,
        "image": "https://cdn.jsdelivr.net/gh/devicons/devicon/icons/github/github-original.svg",
        "category": "VersionControl"
    },
    {
        "_id": 8,
        "skillName": "Java",
        "proficiencyLevel": 4,
        "image": "https://cdn.jsdelivr.net/gh/devicons/devicon/icons/java/java-original-wordmark.svg",
        "category": "Frontend"
    },
    {
        "_id": 9,
        "skillName": "Docker",
        "proficiencyLevel": 4,
        "image": "https://cdn.jsdelivr.net/gh/devicons/devicon/icons/docker/docker-plain-wordmark.svg",
        "category": "VersionControl"
    },
    {
        "_id": 10,
        "skillName": "Figma",
        "proficiencyLevel": 4,
        "image": "https://cdn.jsdelivr.net/gh/devicons/devicon/icons/figma/figma-original.svg",
        "category": "Design"
    },
    {
        "_id": 11,
        "skillName": "Bootstrap",
        "proficiencyLevel": 4,
        "image": "https://cdn.jsdelivr.net/gh/devicons/devicon/icons/bootstrap/bootstrap-plain.svg",
        "category": "Design"
    },
    {
        "_id": 12,
        "skillName": "HTML5",
        "proficiencyLevel": 4,
        "image": "https://cdn.jsdelivr.net/gh/devicons/devicon/icons/html5/html5-plain-wordmark.svg",
        "category": "Frontend"
    },
    {
        "_id": 13,
        "skillName": "CSS",
        "proficiencyLevel": 4,
        "image": "https://cdn.jsdelivr.net/gh/devicons/devicon/icons/css3/css3-plain-wordmark.svg",
        "category": "Design"
    },
    {
        "_id": 14,
        "skillName": "JavaScript",
        "proficiencyLevel": 4,
        "image": "https://cdn.jsdelivr.net/gh/devicons/devicon/icons/javascript/javascript-original.svg",
        "category": "Frontend"
    },
    {
        "_id": 15,
        "skillName": "JQuery",
        "proficiencyLevel": 3,
        "image": "https://cdn.jsdelivr.net/gh/devicons/devicon/icons/jquery/jquery-plain-wordmark.svg",
        "category": "Frontend"
    }
]